colornamer/__init__.py
colornamer/colornamer.py
static/__init__.py
static/color_hierarchy.csv
static/color_hierarchy.json
colornamer-0.2.4.dist-info/LICENSE
colornamer-0.2.4.dist-info/METADATA
colornamer-0.2.4.dist-info/WHEEL
colornamer-0.2.4.dist-info/top_level.txt
colornamer-0.2.4.dist-info/RECORD
