Metadata-Version: 2.1
Name: colornamer
Version: 0.2.4
Summary: Given a color, return a hierarchy of names.
Home-page: https://github.com/stitchfix/colornamer
Author: Dan Tasse
Author-email: dan.tasse@stitchfix.com
License: UNKNOWN
Platform: UNKNOWN
Requires-Python: >=3.7
License-File: LICENSE
Requires-Dist: importlib-resources
Requires-Dist: numpy
Requires-Dist: scikit-image (==0.19.1)
